EXOSIMS/MissionSim.py
EXOSIMS/__init__.py
EXOSIMS/e2eTests.py
EXOSIMS/BackgroundSources/GalaxiesFaintStars.py
EXOSIMS/BackgroundSources/__init__.py
EXOSIMS/BackgroundSources/stellar_cnts.txt
EXOSIMS/Completeness/BrownCompleteness.py
EXOSIMS/Completeness/GarrettCompleteness.py
EXOSIMS/Completeness/IntegrationTimeAdjustedCompleteness.py
EXOSIMS/Completeness/SubtypeCompleteness.py
EXOSIMS/Completeness/__init__.py
EXOSIMS/Observatory/L2_halo_orbit_six_month.mat
EXOSIMS/Observatory/ObservatoryL2Halo.py
EXOSIMS/Observatory/Roman.py
EXOSIMS/Observatory/SotoStarshade.py
EXOSIMS/Observatory/SotoStarshade_ContThrust.py
EXOSIMS/Observatory/SotoStarshade_SKi.py
EXOSIMS/Observatory/SotoStarshade_parallel.py
EXOSIMS/Observatory/WFIRSTObservatoryL2.py
EXOSIMS/Observatory/__init__.py
EXOSIMS/OpticalSystem/KasdinBraems.py
EXOSIMS/OpticalSystem/Nemati.py
EXOSIMS/OpticalSystem/Nemati_2019.py
EXOSIMS/OpticalSystem/__init__.py
EXOSIMS/PlanetPhysicalModel/Forecaster.py
EXOSIMS/PlanetPhysicalModel/ForecasterMod.py
EXOSIMS/PlanetPhysicalModel/ForecasterSousa.py
EXOSIMS/PlanetPhysicalModel/FortneyMarleyCahoyMix1.py
EXOSIMS/PlanetPhysicalModel/__init__.py
EXOSIMS/PlanetPhysicalModel/fortney_table4.mat
EXOSIMS/PlanetPopulation/AlbedoByRadius.py
EXOSIMS/PlanetPopulation/AlbedoByRadiusDulzPlavchan.py
EXOSIMS/PlanetPopulation/Brown2005EarthLike.py
EXOSIMS/PlanetPopulation/DulzPlavchan.py
EXOSIMS/PlanetPopulation/EarthTwinHabZone1.py
EXOSIMS/PlanetPopulation/EarthTwinHabZone1SDET.py
EXOSIMS/PlanetPopulation/EarthTwinHabZone2.py
EXOSIMS/PlanetPopulation/EarthTwinHabZone3.py
EXOSIMS/PlanetPopulation/EarthTwinHabZoneSDET.py
EXOSIMS/PlanetPopulation/Guimond2019.py
EXOSIMS/PlanetPopulation/JupiterTwin.py
EXOSIMS/PlanetPopulation/KeplerLike1.py
EXOSIMS/PlanetPopulation/KeplerLike2.py
EXOSIMS/PlanetPopulation/KnownRVPlanets.py
EXOSIMS/PlanetPopulation/NominalOcc_Radius.csv
EXOSIMS/PlanetPopulation/OptimisticOcc_Radius.csv
EXOSIMS/PlanetPopulation/PessimisticOcc_Radius.csv
exosims-3.6.5.dist-info/licenses/LICENSE
exosims-3.6.5.dist-info/METADATA
exosims-3.6.5.dist-info/WHEEL
exosims-3.6.5.dist-info/top_level.txt
exosims-3.6.5.dist-info/RECORD
