Metadata-Version: 2.4
Name: EXOSIMS
Version: 3.6.5
Summary: Exoplanet Imaging Mission Simulator
Author-email: Dmitry Savransky <ds264@cornell.edu>
Maintainer-email: Dmitry Savransky <ds264@cornell.edu>
License-Expression: BSD-3-Clause
Project-URL: Homepage, https://github.com/dsavransky/EXOSIMS
Project-URL: Documentation, https://exosims.readthedocs.io
Project-URL: Repository, https://github.com/dsavransky/EXOSIMS
Project-URL: Issues, https://github.com/dsavransky/EXOSIMS/issues
Classifier: Development Status :: 5 - Production/Stable
Classifier: Intended Audience :: Education
Classifier: Intended Audience :: Science/Research
Classifier: Topic :: Scientific/Engineering :: Mathematics
Classifier: Topic :: Scientific/Engineering :: Physics
Classifier: Programming Language :: Python :: 3
Classifier: Programming Language :: Python :: 3.10
Classifier: Programming Language :: Python :: 3.11
Classifier: Programming Language :: Python :: 3.12
Classifier: Programming Language :: Python :: 3.13
Requires-Python: >=3.10
License-File: LICENSE
Requires-Dist: numpy>=1.20.0
Requires-Dist: scipy>=1.7.2
Requires-Dist: astropy>=6.0.0
Requires-Dist: jplephem>=2.20.0
Requires-Dist: ortools>=9.0
Requires-Dist: h5py>=3.7.0
Requires-Dist: astroquery>=0.4.8
Requires-Dist: exo-det-box
Requires-Dist: tqdm>=4.59
Requires-Dist: pandas>=1.3
Requires-Dist: MeanStars>=3.4.0
Requires-Dist: synphot>=1.3.0
Requires-Dist: ipyparallel>=8.0.0
Requires-Dist: keplertools>=1.2.1
Requires-Dist: angutils>=1.0.0
Dynamic: license-file
